<annotation>
	<folder>VOC2007</folder>
	<filename>001274.jpg</filename>
	<path>ACID/001274.jpg</path>
	<source>
		<database>Unknown</database>
	</source>
	<size>
		<width>1280</width>
		<height>720</height>
		<depth>3</depth>
	</size>
	<segmented>0</segmented>
	<object>
		<name>dump_truck</name>
		<pose>Unspecified</pose>
		<truncated>0</truncated>
		<difficult>0</difficult>
		<bndbox>
			<xmin>287</xmin>
			<ymin>371</ymin>
			<xmax>657</xmax>
			<ymax>664</ymax>
		</bndbox>
	</object>
	<object>
		<name>excavator</name>
		<pose>Unspecified</pose>
		<truncated>0</truncated>
		<difficult>0</difficult>
		<bndbox>
			<xmin>351</xmin>
			<ymin>46</ymin>
			<xmax>871</xmax>
			<ymax>421</ymax>
		</bndbox>
	</object>
</annotation>