<annotation>
	<folder>VOC2007</folder>
	<filename>001997.jpg</filename>
	<path>ACID/001997.jpg</path>
	<source>
		<database>Unknown</database>
	</source>
	<size>
		<width>1280</width>
		<height>720</height>
		<depth>3</depth>
	</size>
	<segmented>0</segmented>
	<object>
		<name>dump_truck</name>
		<pose>Unspecified</pose>
		<truncated>1</truncated>
		<difficult>0</difficult>
		<bndbox>
			<xmin>1</xmin>
			<ymin>134</ymin>
			<xmax>162</xmax>
			<ymax>224</ymax>
		</bndbox>
	</object>
	<object>
		<name>dump_truck</name>
		<pose>Unspecified</pose>
		<truncated>0</truncated>
		<difficult>0</difficult>
		<bndbox>
			<xmin>242</xmin>
			<ymin>194</ymin>
			<xmax>406</xmax>
			<ymax>371</ymax>
		</bndbox>
	</object>
	<object>
		<name>excavator</name>
		<pose>Unspecified</pose>
		<truncated>0</truncated>
		<difficult>0</difficult>
		<bndbox>
			<xmin>357</xmin>
			<ymin>148</ymin>
			<xmax>799</xmax>
			<ymax>481</ymax>
		</bndbox>
	</object>
</annotation>